pyray/__init__.py
pyray/__init__.pyi
pyray/py.typed
raylib/__init__.py
raylib/__init__.pyi
raylib/_raylib_cffi.cpython-38-x86_64-linux-gnu.so
raylib/build.py
raylib/colors.py
raylib/defines.py
raylib/enums.py
raylib/glfw3.h.modified
raylib/physac.h.modified
raylib/py.typed
raylib/raygui.h.modified
raylib/raylib.h.modified
raylib/raymath.h.modified
raylib/rlgl.h.modified
raylib/version.py
raylib_drm.libs/libEGL-c97c7e07.so.1.0.0
raylib_drm.libs/libX11-xcb-e645c8ef.so.1.0.0
raylib_drm.libs/libXau-4e4d8fc7.so.6.0.0
raylib_drm.libs/libXdmcp-832b8cbe.so.6.0.0
raylib_drm.libs/libboost_filesystem-6916765f.so.1.58.0
raylib_drm.libs/libboost_system-c115ab76.so.1.58.0
raylib_drm.libs/libcapnp-0-1458bf79.5.3.so
raylib_drm.libs/libdrm-d63700ec.so.2.4.0
raylib_drm.libs/libffi-3641885e.so.6.0.4
raylib_drm.libs/libgbm-57b2293e.so.1.0.0
raylib_drm.libs/libglapi-4c8d516a.so.0.0.0
raylib_drm.libs/libkj-0-2efc4b57.5.3.so
raylib_drm.libs/libmirclient-107bfb25.so.9
raylib_drm.libs/libmircommon-5e24eca6.so.7
raylib_drm.libs/libmircore-a245bef3.so.1
raylib_drm.libs/libmirprotobuf-15c4cba0.so.3
raylib_drm.libs/libprotobuf-lite-cc08eaed.so.9.0.1
raylib_drm.libs/libwayland-client-29720bf1.so.0.3.0
raylib_drm.libs/libwayland-server-ea0a3d22.so.0.1.0
raylib_drm.libs/libxcb-98a1a560.so.1.1.0
raylib_drm.libs/libxcb-dri2-e339c353.so.0.0.0
raylib_drm.libs/libxcb-dri3-c1ded2f9.so.0.0.0
raylib_drm.libs/libxcb-present-80027563.so.0.0.0
raylib_drm.libs/libxcb-sync-61e4f7ae.so.1.0.0
raylib_drm.libs/libxcb-xfixes-1442d8c3.so.0.0.0
raylib_drm.libs/libxkbcommon-31c74b80.so.0.0.0
raylib_drm.libs/libxshmfence-8af82335.so.1.0.0
raylib_drm-5.5.0.4.dist-info/LICENSE
raylib_drm-5.5.0.4.dist-info/METADATA
raylib_drm-5.5.0.4.dist-info/WHEEL
raylib_drm-5.5.0.4.dist-info/top_level.txt
raylib_drm-5.5.0.4.dist-info/RECORD
raylib_drm-5.5.0.4.dist-info/sboms/auditwheel.cdx.json
