Metadata-Version: 2.4
Name: raylib_drm
Version: 5.5.0.4
Summary: Python CFFI bindings for Raylib
Home-page: https://github.com/electronstudio/raylib-python-cffi
Author: Electron Studio
Author-email: github@electronstudio.co.uk
Classifier: Programming Language :: Python :: 3
Classifier: Programming Language :: Python :: 3.14
Classifier: Programming Language :: Python :: 3.13
Classifier: Programming Language :: Python :: 3.12
License-File: LICENSE
Requires-Dist: cffi>=1.15.1
Dynamic: author
Dynamic: author-email
Dynamic: classifier
Dynamic: description
Dynamic: description-content-type
Dynamic: home-page
Dynamic: license-file
Dynamic: requires-dist
Dynamic: summary
